vsrc/alu.v
/*
module pg_generate(
    input[3:0] a, b,
    output[3:0] p, g
);
    assign p = a ^ b;
    assign g = a & b;
endmodule

module c_generate(
	input [3:0]p, g,
	input cin,
	output [3:0] cout
);
							
	assign cout[0]=g[0]|cin&p[0];
	assign cout[1]=g[1]|g[0]&p[1]|cin&p[1]&p[0];
	assign cout[2]=g[2]|g[1]&p[2]|g[0]&p[2]&p[1]|cin&p[2]&p[1]&p[0];
	assign cout[3]=g[3]|g[2]&p[3]|g[1]&p[3]&p[2]|g[0]&p[3]&p[2]&p[1]|cin&p[3]&p[2]&p[1]&p[0];

endmodule

module c_generate2bit(
	input [1:0]p, g,
	input cin,
	output [1:0] cout
);		
	assign cout[0]=g[0]|cin&p[0];
	assign cout[1]=g[1]|g[0]&p[1]|cin&p[1]&p[0];
endmodule


module pgm_generate(
    input[3:0] p, g,
    output pm, gm
);
    assign gm=g[3]|g[2]&p[3]|g[1]&p[3]&p[2]|g[0]&p[3]&p[2]&p[1];
	assign pm=p[3]&p[2]&p[1]&p[0];
endmodule


module pgmm_generate(
    input[3:0] pm, gm,
    output pmm, gmm
);
    assign gmm=gm[3]|gm[2]&pm[3]|gm[1]&pm[3]&pm[2]|gm[0]&pm[3]&pm[2]&pm[1];
	assign pmm=pm[3]&pm[2]&pm[1]&pm[0];
endmodule

module Adder_32bit(
    input [31:0]a, b,
    input cin,
    output [31:0]result,
    output cout, overflow, zero;
);
    wire [31:0] p, g, ci;
    wire [7:0] pm, gm, cm;
    wire [1:0] pmm, gmm;
    wire [2:0] cmm;
    assign cmm[0] = cin;
    generate
        genvar i;
        for(i = 0; i< 8; i++)begin
            //第一层的进位生成p与进位控制g
            pg_generate mypg(.a(a[i*4+3: i*4]), .b(b[i*4+3: i*4]), .p(p[i*4+3: i*4]), .g(g[i*4+3: i*4]));
            //根据第二层cm生成的进位来生成第一层进位，第一层进位与p异或获得result
            c_generate myc(.p(p[i*4+3: i*4]), .g(g[i*4+3: i*4]), .cin(cm[i]), .cout(ci[i*4+3: i*4]));
            //第二层的进位生成pm与进位控制gm
            pgm_generate mypgm(.p(p[i*4+3: i*4]), .g(g[i*4+3: i*4]), .pm(pm[i]), .gm(gm[i]));
        end
        genvar j;
        for(j = 0; j < 2; j++)begin
            //第二层进位cm
            c_generate mycm(.p(pm[i*4+3: i*4]), .g(gm[i*4+3: i*4]), .cin(cmm[i]), .cout(cm[i*4+3: i*4]])); 
            //第三层的进位生成pmm与进位控制gmm
            pgmm_generate mypgmm(.pm(pm[j*4+3: j*4]), .gm([j*4+3: j*4]), .pmm(pmm[j]), .gmm(gmm[j]));
        end
    endgenerate
    c_generate2bit mycm2bit(.p(pmm[1:0]), .g(gmm[1:0]), .cin(cmm[0]), .cout(cmm[2:1]]));
    assign result = p ^ ci;
    assign cout = cmm[2];
    assign zero = ~(| result);
    assign overflow = a[31] == b[31] && a[31] != result[31];
endmodule
*/
module Adder_32bit(
    input [31:0]a, b,
    input cin,
    output [31:0]result,
    output cout, overflow, zero
);
    assign {cout, result} = a + b + {31'b0, cin};
    assign zero = ~(| result); 
    assign overflow = a[31] == b[31] && a[31] != result[31];
endmodule

module Shift_32bit(
    input[31:0] a,
    input[4:0] shift_num,
    input[1:0] shift_crl,
    output[31:0] shift_result
);
    localparam SLL = 2'b00;
    localparam SRA = 2'b01;
    localparam SRL = 2'b10;
    wire [31:0] sll_result, sra_result, srl_result;
    assign sll_result = a << shift_num;
    assign sra_result = a >>> shift_num;
    assign srl_result = a << shift_num;
    assign shift_result = (shift_crl == SLL)? sll_result :
                          (shift_crl == SRA)? sra_result :
                          (shift_crl == SRL)? srl_result : a;
endmodule

module Logic_32bit(
    input[31:0] a,b,
    input[1:0] logic_crl,
    output [31:0] logic_result
);
    localparam AND = 2'b00;
    localparam OR  = 2'b01;
    localparam XOR = 2'b10;
    wire [31:0] and_result, or_result, xor_result;
    assign and_result = a & b;
    assign or_result = a | b;
    assign xor_result = a ^ b;
    assign logic_result = (logic_crl == AND)? and_result :
                          (logic_crl == OR )? or_result  :
                          (logic_crl == XOR)? xor_result : a;

endmodule

module Alu_32bit(
    input [31:0] a, b,
    input [3:0] alu_crl,
    input sub, sign,
    output reg [31:0] result,
    output reg ZF, OF, CF
);
    localparam ADDER = 2'b00;
    localparam SHIFT = 2'b01;
    localparam LOGIC = 2'b10;
    localparam CMP   = 2'b11;
    wire[31:0] adder_result, shift_result, logic_result, cmp_result;
    wire[31:0] l, r;
    reg[1:0] shift_crl, logic_crl, op_crl;
    //wire sub;
    assign l = a;
    //assign sub = func == SUB;
    assign r = sub? ~b : b;

    always@(*)begin
        case(alu_crl)
            4'b0000:
            begin
                op_crl = 2'b00;
            end
            default:
            begin
                op_crl = 2'b00;
            end
        endcase
    end
    Adder_32bit Adder(.a(l), .b(r), .cin(sub), .result(adder_result), .cout(CF), .zero(ZF), .overflow(OF));
    Shift_32bit Shift(.a(a), .shift_num(b[4:0]), .shift_crl(shift_crl), .shift_result(shift_result));
    Logic_32bit Logic(.a(a), .b(b), .logic_crl(logic_crl), .logic_result(logic_result));
    
    wire cmp;
    assign cmp = sign ? OF ^ adder_result[31] : CF;
    assign cmp_result = {31'b0, cmp};

    always@(*)begin
        case(op_crl)
            ADDER: result = adder_result;
            SHIFT: result = shift_result;
            LOGIC: result = logic_result;
            CMP  : result = cmp_result;
        endcase
    end


endmodule

vsrc/execute.v
module EXU#(DATA_WIDTH = 32)(
    input [6:0] op,
    input [2:0] func,
    input [DATA_WIDTH-1:0]src1, src2, imm, pc,
    output [DATA_WIDTH-1:0]result,
    output reg[DATA_WIDTH-1:0]upc,
    output reg wen,
    output wire exit, ZF, OF, CF, jump
);

    reg [3:0] alu_op;
    reg sub, sign;
    reg[31:0] a, b;
    always@(*)begin
        case(op)
            7'b0010011:begin //I
                wen = 1;
                a = src1;
                b = imm;
                case(func)
                    3'b000:begin     //addi
                        alu_op = 4'b0000;
                        sub = 0;
                        sign = 0;
                    end
                    default:begin
                        a = src1;
                        b = src2;
                        {alu_op, sub, sign} = 0;
                    end
                endcase
            end
            7'b0010111:begin //auipc
                wen = 1;
                a = pc;
                b = imm;
                alu_op = 4'b0000;
                sub = 0;
                sign = 0; 
            end
            7'b1101111:begin //jal
                wen = 1;
                a = pc;
                b = 32'b100;
                alu_op = 4'b0000;
                sub = 0;
                sign = 0;
                upc = pc + imm;
            end
            7'b1100111:begin //jalr
                wen = 1;
                a = pc;
                b = 32'b100;
                alu_op = 4'b0000;
                sub = 0;
                sign = 0;
                upc = (src1 + imm)&~1;
            end
            7'b0110111:begin //lui
                wen = 1;
                a = 32'b0;
                b = imm;
                alu_op = 4'b0000;
                sub = 0;
                sign = 0; 
            end
            default:begin
                a = src1;
                b = src2;
                {alu_op, sub, sign, wen} = 0;
            end
        endcase
    end
    Alu_32bit myalu(.a(a), .b(b), .alu_crl(alu_op), .sub(sub), .sign(sign), .result(result), .ZF(ZF), .OF(OF), .CF(CF));
    assign jump = (op==7'b1101111)||(op==7'b1100111);
    assign exit = (op==7'b1110011) && (func == 3'b0);
endmodule

vsrc/decode.v
module IDU(
    input[31:0] inst,
    output[6:0] op,
    output[2:0] func,
    output[4:0] rs1, rs2, rd,
    output[31:0] imm
);
    reg[31:0] i;
    assign op = inst[6:0];
    assign func = inst[14:12];
    assign rd = inst[11:7];
    assign rs1 = inst[19:15];
    assign rs2 = inst[24:20];
    
    always@(*)begin
        case(inst[6:0])
            7'b0110111: //lui
            begin
                i = {inst[31:12], 12'b0};
            end
            7'b0010111: // auipc U
            begin
                i = {inst[31:12], 12'b0};
            end
            7'b0000011,
            7'b0010011,
            7'b1100111,
            7'b1110011: //I
            begin
                i = {{20{inst[31]}}, inst[31:20]};
            end
            7'b1101111: //J
            begin
                i = {{11{inst[31]}}, inst[31], inst[19:12], inst[20], inst[30:21], 1'b0};
            end
            7'b0100011: //S
            begin
                i = {{20{inst[31]}}, inst[31:25], inst[11:7]};
            end
            default:
            begin
                i = 32'b0;
            end
        endcase
    end

    assign imm = i;

endmodule

vsrc/reg.v
module RegisterFile #(ADDR_WIDTH = 1, DATA_WIDTH = 1) (
  input clk,
  output [DATA_WIDTH-1:0] rdata1,
  input [ADDR_WIDTH-1:0] raddr1,
  output [DATA_WIDTH-1:0] rdata2,
  input [ADDR_WIDTH-1:0] raddr2,
  input [DATA_WIDTH-1:0] wdata,
  input [ADDR_WIDTH-1:0] waddr,
  input wen
);
  reg [DATA_WIDTH-1:0] rf [2**ADDR_WIDTH-1:0];
  always @(posedge clk) begin
    if (wen) rf[waddr] <= wdata;
  end
  always @(*)begin
      rf[0] = 0;
  end
  assign rdata1 = rf[raddr1];
  assign rdata2 = rf[raddr2];
endmodule

vsrc/pc.v
module PC#(DATA_WIDTH) (
    input clk, rst,
    input [DATA_WIDTH-1 : 0] upc,
    input jump,
    output reg[DATA_WIDTH-1 : 0] pc
);
    always@(posedge clk)begin
        if(rst) pc <= 32'h80000000;
        else if(jump) pc <= upc;
        else pc <= pc + 4;
    end
endmodule

vsrc/top.v
module top #(DATA_WIDTH = 32)(
    input clk,rst,
    input [DATA_WIDTH-1 : 0] inst,
    output reg[DATA_WIDTH-1 : 0] pc, upc,
    output wire exit
);
    wire wen, jump;
    wire [6:0]op;
    wire [2:0]func;
    wire [4:0]rs1, rs2, rd;
    wire [31:0] imm;
    wire ZF, OF, CF;
    wire[DATA_WIDTH-1 : 0] src1, src2; 
    wire[DATA_WIDTH-1:0] result;
    reg wen;
    PC #(DATA_WIDTH) mpc(.clk(clk), .rst(rst), .upc(upc), .jump(jump), .pc(pc));
    RegisterFile #(5, DATA_WIDTH) mreg(.clk(clk),.rdata1(src1),.raddr1(rs1),.rdata2(src2),.raddr2(rs2),.wdata(result),.waddr(rd),.wen(wen)); 
    IDU mdecode(.inst(inst), .op(op), .func(func), .rs1(rs1), .rs2(rs2), .rd(rd), .imm(imm));
    EXU #(DATA_WIDTH) mexecute(.op(op), .func(func), .src1(src1), .src2(src2), .imm(imm), .pc(pc), .result(result), .upc(upc), .wen(wen),.exit(exit),.ZF(ZF),.OF(OF),.CF(CF),.jump(jump));


    endmodule

dump.vcd
$version Generated by VerilatedVcd $end
$timescale 1s $end

 $scope module TOP $end
  $var wire  1 T clk $end
  $var wire  1 Y exit $end
  $var wire 32 V inst [31:0] $end
  $var wire 32 W pc [31:0] $end
  $var wire  1 U rst $end
  $var wire 32 X upc [31:0] $end
  $scope module top $end
   $var wire  1 % CF $end
   $var wire 32 b DATA_WIDTH [31:0] $end
   $var wire  1 $ OF $end
   $var wire  1 # ZF $end
   $var wire  1 T clk $end
   $var wire  1 Y exit $end
   $var wire  3 ] func [2:0] $end
   $var wire 32 a imm [31:0] $end
   $var wire 32 V inst [31:0] $end
   $var wire  1 [ jump $end
   $var wire  7 \ op [6:0] $end
   $var wire 32 W pc [31:0] $end
   $var wire  5 ` rd [4:0] $end
   $var wire 32 ( result [31:0] $end
   $var wire  5 ^ rs1 [4:0] $end
   $var wire  5 _ rs2 [4:0] $end
   $var wire  1 U rst $end
   $var wire 32 & src1 [31:0] $end
   $var wire 32 ' src2 [31:0] $end
   $var wire 32 X upc [31:0] $end
   $var wire  1 Z wen $end
   $scope module mdecode $end
    $var wire  3 ] func [2:0] $end
    $var wire 32 a i [31:0] $end
    $var wire 32 a imm [31:0] $end
    $var wire 32 V inst [31:0] $end
    $var wire  7 \ op [6:0] $end
    $var wire  5 ` rd [4:0] $end
    $var wire  5 ^ rs1 [4:0] $end
    $var wire  5 _ rs2 [4:0] $end
   $upscope $end
   $scope module mexecute $end
    $var wire  1 % CF $end
    $var wire 32 b DATA_WIDTH [31:0] $end
    $var wire  1 $ OF $end
    $var wire  1 # ZF $end
    $var wire 32 ) a [31:0] $end
    $var wire  4 c alu_op [3:0] $end
    $var wire 32 * b [31:0] $end
    $var wire  1 Y exit $end
    $var wire  3 ] func [2:0] $end
    $var wire 32 a imm [31:0] $end
    $var wire  1 [ jump $end
    $var wire  7 \ op [6:0] $end
    $var wire 32 W pc [31:0] $end
    $var wire 32 ( result [31:0] $end
    $var wire  1 d sign $end
    $var wire 32 & src1 [31:0] $end
    $var wire 32 ' src2 [31:0] $end
    $var wire  1 d sub $end
    $var wire 32 X upc [31:0] $end
    $var wire  1 Z wen $end
    $scope module myalu $end
     $var wire  2 e ADDER [1:0] $end
     $var wire  1 % CF $end
     $var wire  2 h CMP [1:0] $end
     $var wire  2 g LOGIC [1:0] $end
     $var wire  1 $ OF $end
     $var wire  2 f SHIFT [1:0] $end
     $var wire  1 # ZF $end
     $var wire 32 ) a [31:0] $end
     $var wire 32 ( adder_result [31:0] $end
     $var wire  4 c alu_crl [3:0] $end
     $var wire 32 * b [31:0] $end
     $var wire  1 % cmp $end
     $var wire 32 - cmp_result [31:0] $end
     $var wire 32 ) l [31:0] $end
     $var wire  2 j logic_crl [1:0] $end
     $var wire 32 , logic_result [31:0] $end
     $var wire  2 e op_crl [1:0] $end
     $var wire 32 * r [31:0] $end
     $var wire 32 ( result [31:0] $end
     $var wire  2 i shift_crl [1:0] $end
     $var wire 32 + shift_result [31:0] $end
     $var wire  1 d sign $end
     $var wire  1 d sub $end
     $scope module Adder $end
      $var wire 32 ) a [31:0] $end
      $var wire 32 * b [31:0] $end
      $var wire  1 d cin $end
      $var wire  1 % cout $end
      $var wire  1 $ overflow $end
      $var wire 32 ( result [31:0] $end
      $var wire  1 # zero $end
     $upscope $end
     $scope module Logic $end
      $var wire  2 e AND [1:0] $end
      $var wire  2 f OR [1:0] $end
      $var wire  2 g XOR [1:0] $end
      $var wire 32 ) a [31:0] $end
      $var wire 32 . and_result [31:0] $end
      $var wire 32 * b [31:0] $end
      $var wire  2 j logic_crl [1:0] $end
      $var wire 32 , logic_result [31:0] $end
      $var wire 32 / or_result [31:0] $end
      $var wire 32 0 xor_result [31:0] $end
     $upscope $end
     $scope module Shift $end
      $var wire  2 e SLL [1:0] $end
      $var wire  2 f SRA [1:0] $end
      $var wire  2 g SRL [1:0] $end
      $var wire 32 ) a [31:0] $end
      $var wire  2 i shift_crl [1:0] $end
      $var wire  5 1 shift_num [4:0] $end
      $var wire 32 + shift_result [31:0] $end
      $var wire 32 2 sll_result [31:0] $end
      $var wire 32 3 sra_result [31:0] $end
      $var wire 32 2 srl_result [31:0] $end
     $upscope $end
    $upscope $end
   $upscope $end
   $scope module mpc $end
    $var wire 32 b DATA_WIDTH [31:0] $end
    $var wire  1 T clk $end
    $var wire  1 [ jump $end
    $var wire 32 W pc [31:0] $end
    $var wire  1 U rst $end
    $var wire 32 X upc [31:0] $end
   $upscope $end
   $scope module mreg $end
    $var wire 32 k ADDR_WIDTH [31:0] $end
    $var wire 32 b DATA_WIDTH [31:0] $end
    $var wire  1 T clk $end
    $var wire  5 ^ raddr1 [4:0] $end
    $var wire  5 _ raddr2 [4:0] $end
    $var wire 32 & rdata1 [31:0] $end
    $var wire 32 ' rdata2 [31:0] $end
    $var wire 32 4 rf[0] [31:0] $end
    $var wire 32 > rf[10] [31:0] $end
    $var wire 32 ? rf[11] [31:0] $end
    $var wire 32 @ rf[12] [31:0] $end
    $var wire 32 A rf[13] [31:0] $end
    $var wire 32 B rf[14] [31:0] $end
    $var wire 32 C rf[15] [31:0] $end
    $var wire 32 D rf[16] [31:0] $end
    $var wire 32 E rf[17] [31:0] $end
    $var wire 32 F rf[18] [31:0] $end
    $var wire 32 G rf[19] [31:0] $end
    $var wire 32 5 rf[1] [31:0] $end
    $var wire 32 H rf[20] [31:0] $end
    $var wire 32 I rf[21] [31:0] $end
    $var wire 32 J rf[22] [31:0] $end
    $var wire 32 K rf[23] [31:0] $end
    $var wire 32 L rf[24] [31:0] $end
    $var wire 32 M rf[25] [31:0] $end
    $var wire 32 N rf[26] [31:0] $end
    $var wire 32 O rf[27] [31:0] $end
    $var wire 32 P rf[28] [31:0] $end
    $var wire 32 Q rf[29] [31:0] $end
    $var wire 32 6 rf[2] [31:0] $end
    $var wire 32 R rf[30] [31:0] $end
    $var wire 32 S rf[31] [31:0] $end
    $var wire 32 7 rf[3] [31:0] $end
    $var wire 32 8 rf[4] [31:0] $end
    $var wire 32 9 rf[5] [31:0] $end
    $var wire 32 : rf[6] [31:0] $end
    $var wire 32 ; rf[7] [31:0] $end
    $var wire 32 < rf[8] [31:0] $end
    $var wire 32 = rf[9] [31:0] $end
    $var wire  5 ` waddr [4:0] $end
    $var wire 32 ( wdata [31:0] $end
    $var wire  1 Z wen $end
   $upscope $end
  $upscope $end
 $upscope $end
$enddefinitions $end


#1
1#
0$
0%
b00000000000000000000000000000000 &
b00000000000000000000000000000000 '
b00000000000000000000000000000000 (
b00000000000000000000000000000000 )
b00000000000000000000000000000000 *
b00000000000000000000000000000000 +
b00000000000000000000000000000000 ,
b00000000000000000000000000000000 -
b00000000000000000000000000000000 .
b00000000000000000000000000000000 /
b00000000000000000000000000000000 0
b00000 1
b00000000000000000000000000000000 2
b00000000000000000000000000000000 3
b00000000000000000000000000000000 4
b00000000000000000000000000000000 5
b00000000000000000000000000000000 6
b00000000000000000000000000000000 7
b00000000000000000000000000000000 8
b00000000000000000000000000000000 9
b00000000000000000000000000000000 :
b00000000000000000000000000000000 ;
b00000000000000000000000000000000 <
b00000000000000000000000000000000 =
b00000000000000000000000000000000 >
b00000000000000000000000000000000 ?
b00000000000000000000000000000000 @
b00000000000000000000000000000000 A
b00000000000000000000000000000000 B
b00000000000000000000000000000000 C
b00000000000000000000000000000000 D
b00000000000000000000000000000000 E
b00000000000000000000000000000000 F
b00000000000000000000000000000000 G
b00000000000000000000000000000000 H
b00000000000000000000000000000000 I
b00000000000000000000000000000000 J
b00000000000000000000000000000000 K
b00000000000000000000000000000000 L
b00000000000000000000000000000000 M
b00000000000000000000000000000000 N
b00000000000000000000000000000000 O
b00000000000000000000000000000000 P
b00000000000000000000000000000000 Q
b00000000000000000000000000000000 R
b00000000000000000000000000000000 S
0T
1U
b00000000000000000000000000000000 V
b00000000000000000000000000000000 W
b00000000000000000000000000000000 X
0Y
0Z
0[
b0000000 \
b000 ]
b00000 ^
b00000 _
b00000 `
b00000000000000000000000000000000 a
b00000000000000000000000000100000 b
b0000 c
0d
b00 e
b01 f
b10 g
b11 h
b00 i
b00 j
b00000000000000000000000000000101 k
#2
1T
b10000000000000000000000000000000 W
#3
0T
#4
1T
#5
0#
b00000000000000000000000000000001 (
b00000000000000000000000000000001 *
b00000000000000000000000000000001 /
b00000000000000000000000000000001 0
b00001 1
0T
0U
b00000000000100000000010100010011 V
1Z
b0010011 \
b00001 _
b01010 `
b00000000000000000000000000000001 a
#6
b00000000000000000000000000000001 >
1T
b10000000000000000000000000000100 W
#7
b10000000000000001001000000000100 (
b10000000000000000000000000000100 )
b00000000000000001001000000000000 *
b10000000000000000000000000000100 +
b10000000000000001001000000000100 /
b10000000000000001001000000000100 0
b00000 1
b10000000000000000000000000000100 2
b10000000000000000000000000000100 3
0T
b00000000000000001001000100010111 V
b0010111 \
b001 ]
b00001 ^
b00000 _
b00010 `
b00000000000000001001000000000000 a
#8
b10000000000000001001000000001000 (
b10000000000000000000000000001000 )
b10000000000000000000000000001000 +
b10000000000000001001000000001000 /
b10000000000000001001000000001000 0
b10000000000000000000000000001000 2
b10000000000000000000000000001000 3
b10000000000000001001000000000100 6
1T
b10000000000000000000000000001000 W
#9
b00000000000000000000000000000001 &
b00000000000000000000000000000010 (
b00000000000000000000000000000001 )
b00000000000000000000000000000001 *
b00000000000000000000000000000010 +
b00000000000000000000000000000001 ,
b00000000000000000000000000000001 .
b00000000000000000000000000000001 /
b00000000000000000000000000000000 0
b00001 1
b00000000000000000000000000000010 2
b00000000000000000000000000000000 3
0T
b00000000000101010000010100010011 V
b0010011 \
b000 ]
b01010 ^
b00001 _
b01010 `
b00000000000000000000000000000001 a
#10
b00000000000000000000000000000010 &
b00000000000000000000000000000011 (
b00000000000000000000000000000010 )
b00000000000000000000000000000100 +
b00000000000000000000000000000000 ,
b00000000000000000000000000000000 .
b00000000000000000000000000000011 /
b00000000000000000000000000000011 0
b00000000000000000000000000000100 2
b00000000000000000000000000000001 3
b00000000000000000000000000000010 >
1T
b10000000000000000000000000001100 W
#11
0T
#12
b00000000000000000000000000000011 &
b00000000000000000000000000000100 (
b00000000000000000000000000000011 )
b00000000000000000000000000000110 +
b00000000000000000000000000000001 ,
b00000000000000000000000000000001 .
b00000000000000000000000000000010 0
b00000000000000000000000000000110 2
b00000000000000000000000000000011 >
1T
b10000000000000000000000000010000 W
#13
1#
b00000000000000000000000000000000 &
b00000000000000000000000000000000 (
b00000000000000000000000000000000 )
b00000000000000000000000000000000 *
b00000000000000000000000000000000 +
b00000000000000000000000000000000 ,
b00000000000000000000000000000000 .
b00000000000000000000000000000000 /
b00000000000000000000000000000000 0
b00000 1
b00000000000000000000000000000000 2
b00000000000000000000000000000000 3
0T
b00000000000100000000000001110011 V
1Y
0Z
b1110011 \
b00000 ^
b00000 `
#14
1T
b10000000000000000000000000010100 W
